<?xml version="1.0" encoding="UTF-8" standalone="yes"?>
<p:sld xmlns:a="http://schemas.openxmlformats.org/drawingml/2006/main" xmlns:r="http://schemas.openxmlformats.org/officeDocument/2006/relationships" xmlns:p="http://schemas.openxmlformats.org/presentationml/2006/main"><p:cSld><p:spTree><p:nvGrpSpPr><p:cNvPr id="1" name=""><a:extLst><a:ext uri="{FF2B5EF4-FFF2-40B4-BE49-F238E27FC236}"><a16:creationId xmlns:a16="http://schemas.microsoft.com/office/drawing/2014/main" id="{0D83CEAB-B961-070D-D594-78161EF82EDA}"/></a:ext></a:extLst></p:cNvPr><p:cNvGrpSpPr/><p:nvPr/></p:nvGrpSpPr><p:grpSpPr><a:xfrm><a:off x="0" y="0"/><a:ext cx="0" cy="0"/><a:chOff x="0" y="0"/><a:chExt cx="0" cy="0"/></a:xfrm></p:grpSpPr><p:sp><p:nvSpPr><p:cNvPr id="4" name="タイトル 3"><a:extLst><a:ext uri="{FF2B5EF4-FFF2-40B4-BE49-F238E27FC236}"><a16:creationId xmlns:a16="http://schemas.microsoft.com/office/drawing/2014/main" id="{24FD5989-4377-4DE5-AEDF-2543C939AB2A}"/></a:ext></a:extLst></p:cNvPr><p:cNvSpPr><a:spLocks noGrp="1"/></p:cNvSpPr><p:nvPr><p:ph type="title"/></p:nvPr></p:nvSpPr><p:spPr><a:xfrm><a:off x="684211" y="411480"/><a:ext cx="9173021" cy="950976"/></a:xfrm></p:spPr><p:txBody><a:bodyPr><a:normAutofit/></a:bodyPr><a:lstStyle/><a:p><a:r><a:rPr lang="en-US" altLang="ja-JP" sz="5400" dirty="0"><a:latin typeface="HGS明朝B" panose="02020800000000000000" pitchFamily="18" charset="-128"/><a:ea typeface="HGS明朝B" panose="02020800000000000000" pitchFamily="18" charset="-128"/></a:rPr><a:t>3</a:t></a:r><a:r><a:rPr lang="ja-JP" altLang="en-US" sz="5400" dirty="0"><a:latin typeface="HGS明朝B" panose="02020800000000000000" pitchFamily="18" charset="-128"/><a:ea typeface="HGS明朝B" panose="02020800000000000000" pitchFamily="18" charset="-128"/></a:rPr><a:t>章</a:t></a:r><a:r><a:rPr lang="en-US" altLang="ja-JP" sz="5400" dirty="0"><a:latin typeface="HGS明朝B" panose="02020800000000000000" pitchFamily="18" charset="-128"/><a:ea typeface="HGS明朝B" panose="02020800000000000000" pitchFamily="18" charset="-128"/></a:rPr><a:t>:</a:t></a:r><a:r><a:rPr lang="ja-JP" altLang="en-US" sz="5400" dirty="0"><a:latin typeface="HGS明朝B" panose="02020800000000000000" pitchFamily="18" charset="-128"/><a:ea typeface="HGS明朝B" panose="02020800000000000000" pitchFamily="18" charset="-128"/></a:rPr><a:t>共同開発をしてみよう</a:t></a:r></a:p></p:txBody></p:sp><p:sp><p:nvSpPr><p:cNvPr id="5" name="テキスト プレースホルダー 4"><a:extLst><a:ext uri="{FF2B5EF4-FFF2-40B4-BE49-F238E27FC236}"><a16:creationId xmlns:a16="http://schemas.microsoft.com/office/drawing/2014/main" id="{0A106487-489C-CA7B-5E88-196E9ABE0904}"/></a:ext></a:extLst></p:cNvPr><p:cNvSpPr><a:spLocks noGrp="1"/></p:cNvSpPr><p:nvPr><p:ph type="body" idx="1"/></p:nvPr></p:nvSpPr><p:spPr><a:xfrm><a:off x="684211" y="1362456"/><a:ext cx="4189541" cy="5202936"/></a:xfrm></p:spPr><p:txBody><a:bodyPr><a:normAutofit/></a:bodyPr><a:lstStyle/><a:p><a:r><a:rPr lang="en-US" altLang="ja-JP" sz="2800" dirty="0"/><a:t>4:</a:t></a:r><a:r><a:rPr lang="ja-JP" altLang="en-US" sz="2800" dirty="0"/><a:t>共同開発のマナー</a:t></a:r></a:p><a:p><a:r><a:rPr lang="ja-JP" altLang="en-US" sz="2000" dirty="0"/><a:t>②勝手にマージしない</a:t></a:r><a:endParaRPr lang="en-US" altLang="ja-JP" sz="2000" dirty="0"/></a:p><a:p><a:r><a:rPr lang="ja-JP" altLang="en-US" sz="2000" dirty="0"/><a:t>予期せぬマージで混乱することは多いです。</a:t></a:r><a:endParaRPr lang="en-US" altLang="ja-JP" sz="2000" dirty="0"/></a:p><a:p><a:r><a:rPr lang="ja-JP" altLang="en-US" sz="2000" dirty="0"/><a:t>一声掛ける・許可をもらう等</a:t></a:r><a:endParaRPr lang="en-US" altLang="ja-JP" sz="2000" dirty="0"/></a:p><a:p><a:r><a:rPr lang="ja-JP" altLang="en-US" sz="2000" dirty="0"/><a:t>してからマージしましょう。</a:t></a:r><a:endParaRPr lang="en-US" altLang="ja-JP" sz="2000" dirty="0"/></a:p></p:txBody></p:sp></p:spTree><p:extLst><p:ext uri="{BB962C8B-B14F-4D97-AF65-F5344CB8AC3E}"><p14:creationId xmlns:p14="http://schemas.microsoft.com/office/powerpoint/2010/main" val="1613302339"/></p:ext></p:extLst></p:cSld><p:clrMapOvr><a:masterClrMapping/></p:clrMapOvr></p:sld>